datayoga/__init__.py
datayoga/__main__.py
datayoga/cli_helpers.py
datayoga-1.134.0.dist-info/METADATA
datayoga-1.134.0.dist-info/WHEEL
datayoga-1.134.0.dist-info/entry_points.txt
datayoga-1.134.0.dist-info/RECORD
