Metadata-Version: 2.1
Name: datayoga
Version: 1.134.0
Summary: DataYoga command line interface
License: Apache-2.0
Author: DataYoga
Author-email: admin@datayoga.io
Requires-Python: >=3.8,<4.0
Classifier: Development Status :: 4 - Beta
Classifier: Intended Audience :: Developers
Classifier: License :: OSI Approved :: Apache Software License
Classifier: Programming Language :: Python :: 3
Classifier: Programming Language :: Python :: 3.8
Classifier: Programming Language :: Python :: 3.9
Classifier: Programming Language :: Python :: 3.10
Classifier: Programming Language :: Python :: 3.11
Classifier: Programming Language :: Python :: 3.12
Classifier: Programming Language :: Python :: 3.13
Classifier: Topic :: Database
Provides-Extra: test
Requires-Dist: PyYAML (>=6.0,<7.0)
Requires-Dist: certifi (>=2023.7.22,<2024.0.0)
Requires-Dist: click (>=8.0.3,<9.0.0)
Requires-Dist: datayoga-core (==1.*)
Requires-Dist: jsonschema (>=4.4.0,<5.0.0)
Requires-Dist: mock (>=4.0.3,<5.0.0) ; extra == "test"
Requires-Dist: pytest (>=7.1.2,<8.0.0) ; extra == "test"
Requires-Dist: pytest-asyncio (>=0.20.1,<0.21.0)
Requires-Dist: pytest-describe (>=2.0.1,<3.0.0) ; extra == "test"
Requires-Dist: pytest-mock (>=3.7.0,<4.0.0) ; extra == "test"
Requires-Dist: pytest-timeout (>=2.1.0,<3.0.0) ; extra == "test"
Requires-Dist: requests-mock (>=1.9.3,<2.0.0) ; extra == "test"
Project-URL: url, https://datayoga.io
